{
  "swagger": "2.0",
  "info": {
    "title": "Access Guard as a Service",
    "version": "dev",
    "contact": {
      "name": "Guard project of Hugs Platform",
      "url": "https://github.com/kamilsk/guard",
      "email": "info@octolab.org"
    }
  },
  "schemes": [
    "http",
    "https"
  ],
  "consumes": [
    "application/json"
  ],
  "produces": [
    "application/json"
  ],
  "paths": {
    "/api/v1/license/extend": {
      "put": {
        "operationId": "Extend",
        "responses": {
          "200": {
            "description": "",
            "schema": {
              "$ref": "#/definitions/grpcExtendLicenseResponse"
            }
          }
        },
        "tags": [
          "License"
        ]
      }
    },
    "/api/v1/license/register": {
      "post": {
        "operationId": "Register",
        "responses": {
          "200": {
            "description": "",
            "schema": {
              "$ref": "#/definitions/grpcRegisterLicenseResponse"
            }
          }
        },
        "tags": [
          "License"
        ]
      }
    },
    "/api/v1/license/{id}": {
      "get": {
        "operationId": "Read",
        "responses": {
          "200": {
            "description": "",
            "schema": {
              "$ref": "#/definitions/grpcReadLicenseResponse"
            }
          }
        },
        "parameters": [
          {
            "name": "id",
            "in": "path",
            "required": true,
            "type": "string"
          }
        ],
        "tags": [
          "License"
        ]
      }
    }
  },
  "definitions": {
    "grpcExtendLicenseResponse": {
      "type": "object"
    },
    "grpcReadLicenseResponse": {
      "type": "object"
    },
    "grpcRegisterLicenseResponse": {
      "type": "object"
    }
  }
}
